README.md
setup.cfg
setup.py
dash_keycloak_2.egg-info/PKG-INFO
dash_keycloak_2.egg-info/SOURCES.txt
dash_keycloak_2.egg-info/dependency_links.txt
dash_keycloak_2.egg-info/requires.txt
dash_keycloak_2.egg-info/top_level.txt
flask_keycloak/__init__.py
flask_keycloak/core.py
flask_keycloak/examples/__init__.py
flask_keycloak/examples/dash_example.py