Metadata-Version: 2.1
Name: dash-keycloak-2
Version: 0.0.18
Summary: Flask extension providing Keycloak integration via the python-keycloak package
Home-page: https://github.com/
Author: Emil Haldrup Eriksen
Author-email: emil.h.eriksen@gmail.com
License: MIT
Platform: UNKNOWN
Classifier: Programming Language :: Python :: 3
